sev3rance_auth_templates/__init__.py
sev3rance_auth_templates/apps.py
sev3rance_auth_templates/static/sev3rance_auth_templates/css/community-apps-fixes.css
sev3rance_auth_templates/static/sev3rance_auth_templates/css/community-apps-fixes.min.css
sev3rance_auth_templates/static/sev3rance_auth_templates/css/community-apps-fixes.min.css.map
sev3rance_auth_templates/static/sev3rance_auth_templates/css/sev3rance.css
sev3rance_auth_templates/static/sev3rance_auth_templates/css/sev3rance.min.css
sev3rance_auth_templates/static/sev3rance_auth_templates/css/sev3rance.min.css.map
sev3rance_auth_templates/static/sev3rance_auth_templates/favicons/README.md
sev3rance_auth_templates/static/sev3rance_auth_templates/favicons/android-chrome-144x144.png
sev3rance_auth_templates/static/sev3rance_auth_templates/favicons/android-chrome-192x192.png
sev3rance_auth_templates/static/sev3rance_auth_templates/favicons/android-chrome-256x256.png
sev3rance_auth_templates/static/sev3rance_auth_templates/favicons/android-chrome-36x36.png
sev3rance_auth_templates/static/sev3rance_auth_templates/favicons/android-chrome-384x384.png
sev3rance_auth_templates/static/sev3rance_auth_templates/favicons/android-chrome-48x48.png
sev3rance_auth_templates/static/sev3rance_auth_templates/favicons/android-chrome-512x512.png
sev3rance_auth_templates/static/sev3rance_auth_templates/favicons/android-chrome-72x72.png
sev3rance_auth_templates/static/sev3rance_auth_templates/favicons/android-chrome-96x96.png
sev3rance_auth_templates/static/sev3rance_auth_templates/favicons/apple-touch-icon-114x114-precomposed.png
sev3rance_auth_templates/static/sev3rance_auth_templates/favicons/apple-touch-icon-114x114.png
sev3rance_auth_templates/static/sev3rance_auth_templates/favicons/apple-touch-icon-120x120-precomposed.png
sev3rance_auth_templates/static/sev3rance_auth_templates/favicons/apple-touch-icon-120x120.png
sev3rance_auth_templates/static/sev3rance_auth_templates/favicons/apple-touch-icon-144x144-precomposed.png
sev3rance_auth_templates-1.7.0.dist-info/METADATA
sev3rance_auth_templates-1.7.0.dist-info/WHEEL
sev3rance_auth_templates-1.7.0.dist-info/licenses/LICENSE
sev3rance_auth_templates-1.7.0.dist-info/RECORD
