Metadata-Version: 2.1
Name: sev3rance-auth-templates
Version: 1.7.0
Summary: Sev3rance Template Overrides for Alliance Auth
Project-URL: Changelog, https://github.com/sev3rance/sev3rance-auth-templates/blob/master/CHANGELOG.md
Project-URL: Documentation, https://github.com/sev3rance/sev3rance-auth-templates/blob/master/README.md
Project-URL: Donations, https://ko-fi.com/ppfeufer
Project-URL: Homepage, https://github.com/sev3rance/sev3rance-auth-templates
Project-URL: Source, https://github.com/sev3rance/sev3rance-auth-templates.git
Project-URL: Tracker, https://github.com/sev3rance/sev3rance-auth-templates/issues
Author-email: Peter Pfeufer <develop@ppfeufer.de>
License:                     GNU GENERAL PUBLIC LICENSE
License-File: LICENSE
Keywords: allianceauth,eveonline,sev3rance,template,template_override
Classifier: Environment :: Web Environment
Classifier: Framework :: Django
Classifier: Framework :: Django :: 4.0
Classifier: Intended Audience :: Developers
Classifier: License :: OSI Approved :: GNU General Public License v3 (GPLv3)
Classifier: Operating System :: OS Independent
Classifier: Programming Language :: Python
Classifier: Programming Language :: Python :: 3 :: Only
Classifier: Programming Language :: Python :: 3.8
Classifier: Programming Language :: Python :: 3.9
Classifier: Programming Language :: Python :: 3.10
Classifier: Programming Language :: Python :: 3.11
Classifier: Topic :: Internet :: WWW/HTTP
Classifier: Topic :: Internet :: WWW/HTTP :: Dynamic Content
Requires-Python: ~=3.8
Requires-Dist: allianceauth>=3.6.1
